{
  "platform": "nextjs",
  "code": {
    "lang": "js",
    "scheme": "blackbox",
    "reactRuntime": "classic"
  },
  "style": {
    "scheme": "css-modules",
    "defaultStyleCssFilePath": "plasmic/plasmic__default_style.css"
  },
  "images": {
    "scheme": "public-files",
    "publicDir": "../public",
    "publicUrlPrefix": "/"
  },
  "tokens": {
    "scheme": "theo",
    "tokensFilePath": "plasmic-tokens.theo.json"
  },
  "srcDir": "components",
  "defaultPlasmicDir": "./plasmic",
  "projects": [
    {
      "projectId": "gVh4qvKgAvpoYwEsjKrFRZ",
      "projectApiToken": "QfOtVHnosBNFVBrRObFpfL8JmylWkR0xYxCiWClZC5Wo7nZowcOGAhnavdyp0lWSymCVokMguane0NjfKsxw",
      "projectName": "Website starter",
      "version": "latest",
      "cssFilePath": "plasmic/website_starter/plasmic.module.css",
      "components": [
        {
          "id": "_UyBW-WtH69k",
          "name": "Homepage",
          "type": "managed",
          "projectId": "gVh4qvKgAvpoYwEsjKrFRZ",
          "renderModuleFilePath": "plasmic/website_starter/PlasmicHomepage.jsx",
          "importSpec": {
            "modulePath": "../pages/index.jsx"
          },
          "cssFilePath": "plasmic/website_starter/PlasmicHomepage.module.css",
          "scheme": "blackbox",
          "componentType": "page",
          "path": "/"
        }
      ],
      "icons": [],
      "images": [],
      "indirect": false,
      "globalContextsFilePath": "",
      "splitsProviderFilePath": "",
      "codeComponents": [
        {
          "id": "J8YC6kBVI14g",
          "name": "PlasmicHead",
          "displayName": "hostless-plasmic-head",
          "componentImportPath": "@plasmicapp/react-web"
        },
        {
          "id": "cWCY-z_EfdRx",
          "name": "Fetcher",
          "displayName": "plasmic-data-source-fetcher",
          "componentImportPath": "@plasmicapp/react-web/lib/data-sources"
        }
      ],
      "customFunctions": []
    }
  ],
  "globalVariants": {
    "variantGroups": [
      {
        "id": "Wrj0n_pL7CnX",
        "name": "Screen",
        "projectId": "gVh4qvKgAvpoYwEsjKrFRZ",
        "contextFilePath": "plasmic/website_starter/PlasmicGlobalVariant__Screen.jsx"
      }
    ]
  },
  "wrapPagesWithGlobalContexts": true,
  "nextjsConfig": {
    "pagesDir": "../pages"
  },
  "cliVersion": "0.1.340",
  "$schema": "https://unpkg.com/@plasmicapp/cli@0.1.340/dist/plasmic.schema.json"
}
